{"nodes":[
{"id":"eco_mesopotamia_irrigation","t":"灌溉起源 · 美索不达米亚运河","d":"eco","y":-6000,"sub":"agri","lat":34.2,"lon":43.9,"w":2,"gist":"把河水引进农田的那一刻,收成第一次不用看老天爷脸色。","detail":"幼发拉底与底格里斯河水量不稳,美索不达米亚人在旱季开渠引水漫灌田地,把靠天吃饭的农业变成可规划的生产。稳定的余粮支撑起城市人口与专职阶层,也带来水权分配与官僚管理的最早雏形,为苏美尔城邦的兴起打下物质基础。","links":["sumer"],"src":"两河流域"},
{"id":"eco_qanat_origin","t":"坎儿井 · 波斯坎儿井暗渠","d":"eco","y":-700,"sub":"agri","lat":34.35,"lon":58.68,"w":1,"gist":"把水渠埋进地下,沙漠里蒸发不掉的水才能走完全程。","detail":"波斯高原干旱少雨,居民凿井后在地下挖掘缓坡暗渠,把山麓地下水引到远处绿洲,渠身埋于地表之下大幅减少蒸发渗漏。这套坎儿井技术后来沿丝路向东传播,在新疆吐鲁番等干旱盆地生根,至今仍是当地重要灌溉水源。","links":["persia"],"src":"坎儿井"},
{"id":"eco_andean_terrace","t":"安第斯梯田","d":"eco","y":800,"sub":"agri","lat":-15.65,"lon":-71.85,"w":1,"gist":"把陡坡削成台阶,安第斯人在悬崖上种出了平地。","detail":"瓦里文化时期,安第斯山民已在陡峭山坡上垒石筑台、修出层层梯田,配合灌溉水渠在多变的高原气候里稳定产出玉米与马铃薯。印加帝国兴起后把这套体系推广到整个安第斯山谷,梯田至今仍是当地农业景观的核心。","links":[],"src":"安第斯梯田"},
{"id":"eco_norfolk_rotation","t":"诺福克轮作制","d":"eco","y":1730,"sub":"agri","lat":52.6,"lon":1.0,"w":2,"gist":"让土地轮流种谷物、萝卜、牧草,休耕从此成了浪费。","detail":"英格兰诺福克郡农民摸索出小麦、萝卜、大麦与三叶草四茬轮作法,用根茎与豆科作物自然恢复地力,取代了旧式休耕。轮作还顺带多养出饲料喂牲畜,肉类与谷物同时增产,为随后的人口增长与圈地扩张提供了余粮基础。","links":["eco_enclosure_movement","industrial"],"src":"诺福克轮作制"},
{"id":"eco_enclosure_movement","t":"圈地运动","d":"eco","y":1760,"sub":"agri","lat":52.0,"lon":-0.5,"w":2,"gist":"公共牧场被围上篱笆分给地主,农民从此只能进城打工。","detail":"英国议会以立法形式把中世纪遗留的公共农地与牧场圈围为私人地产,失去传统用地权的小农被迫离开乡村。集中地权让大农场得以采用新式轮作与农具提升效率,同时把大批劳动力推向正在兴起的工厂,成为工业革命的劳动力来源之一。","links":["industrial"],"src":"圈地运动"},
{"id":"eco_mccormick_reaper","t":"机械收割机 · 麦考密克","d":"eco","y":1831,"sub":"agri","lat":37.8,"lon":-79.2,"w":1,"gist":"一台马拉的机器顶替十个挥镰刀的人,收割从此按小时算。","detail":"弗吉尼亚农场主麦考密克造出一台马拉式机械收割机,靠往复刀片与分禾装置替代人工挥镰,单日收割效率数倍于人力。此后他在芝加哥建厂批量生产,收割机随铁路网销往美国中西部新开垦的大平原,让少数农民就能耕种大片土地。","links":["eco_tractor_mechanization"],"src":"麦考密克收割机"},
{"id":"eco_postwar_fertilizer","t":"化肥革命 · 战后氮肥普及","d":"eco","y":1946,"sub":"agri","lat":34.75,"lon":-87.67,"w":2,"gist":"造炸药的工厂改产肥料,战争剩下的产能喂饱了和平年代的农田。","detail":"二战期间美国为军火大规模建设的合成氨与硝酸铵工厂,战后被改造转产农用氮肥,廉价氮肥产量陡增。美国及后续多国农户开始大量施用化肥,谷物单产在此后数十年持续攀升,农业增产第一次主要依赖工厂而不是新开垦的土地。","links":["eco_hybrid_rice_yuan"],"src":"化学肥料"},
{"id":"eco_hybrid_rice_yuan","t":"杂交水稻 · 袁隆平","d":"eco","y":1973,"sub":"agri","lat":27.35,"lon":110.22,"w":3,"gist":"让水稻自交也能保持杂交优势,亩产从此多养活好几张嘴。","detail":"袁隆平团队在湖南发现野生不育株并培育出三系配套杂交水稻,解决了水稻这种自花授粉作物大规模利用杂交优势的技术难题,单产比常规稻提高两成以上。此后杂交水稻在中国及多个亚非国家推广种植,显著缓解了人口稠密地区的粮食安全压力。","links":["reform_cn"],"src":"袁隆平"},
{"id":"eco_tractor_mechanization","t":"拖拉机 · 农业动力机械化","d":"eco","y":1892,"sub":"agri","lat":43.15,"lon":-91.33,"w":1,"gist":"用发动机代替骡马拉犁,农民第一次不用先喂饱牲口才能下地。","detail":"爱荷华州发明家弗罗利希把汽油发动机装上底盘造出第一台可自行驱动的拖拉机,替代此前依赖骡马或笨重蒸汽牵引机的耕作方式。此后数十年间,汽油拖拉机逐步在欧美农场普及,把畜力占用的饲料用地解放出来,单个农民可耕种的面积大幅扩大。","links":["eco_postwar_fertilizer"],"src":"拖拉机"},
{"id":"eco_refrigerated_shipping","t":"冷链运输 · 冷冻船跨洋运肉","d":"eco","y":1882,"sub":"agri","lat":-45.82,"lon":170.62,"w":1,"gist":"把船舱冻成移动冰箱,南半球的羊肉第一次能跨越赤道卖到伦敦餐桌。","detail":"但尼丁号货船加装氨压缩制冷设备,把冷冻羊肉从新西兰经赤道运抵伦敦仍保持肉质新鲜,标志远洋冷藏运输技术首次实用化。长途冷链的可行性让澳大利亚、新西兰与阿根廷的牧场得以稳定供应欧洲城市,重塑了全球农牧产品的贸易版图。","links":["globalization"],"src":"冷链物流"},
{"id":"eco_spinning_machinery","t":"纺织机械 · 珍妮机与水力纺纱机","d":"eco","y":1764,"sub":"industry","lat":53.75,"lon":-2.48,"w":2,"gist":"一个人能同时纺八个线锭,家庭作坊第一次干不过一台机器。","detail":"兰开夏郡织工哈格里夫斯造出珍妮纺纱机,一人可同时操作数个纱锭;阿克莱特随后发明靠水车驱动的水力纺纱机,纺纱效率与产量大幅超越手摇纺车。纺纱环节率先实现机械化,倒逼织布环节跟进革新,把纺织业从家庭作坊推入工厂体系。","links":["industrial"],"src":"珍妮纺纱机"},
{"id":"eco_bessemer_steel","t":"贝塞麦炼钢法","d":"eco","y":1856,"sub":"industry","lat":53.38,"lon":-1.47,"w":2,"gist":"往铁水里吹一阵风,除杂脱碳的活从几天缩短到几十分钟。","detail":"英国发明家贝塞麦发现向熔融生铁中鼓入空气可快速氧化掉多余碳与杂质,把原本需要数日的炼钢工序压缩到二十多分钟,单炉产量成倍提升。廉价优质钢材由此得以大规模量产,取代熟铁成为铁轨、桥梁与船体的主要材料。","links":["worldwars"],"src":"贝塞麦炼钢法"},
{"id":"eco_scientific_management","t":"泰勒制 · 科学管理法","d":"eco","y":1911,"sub":"industry","lat":39.95,"lon":-75.16,"w":1,"gist":"用秒表量每个动作,工厂第一次把经验换成了可复制的标准流程。","detail":"工程师泰勒在费城钢铁厂用秒表拆解工人的每个操作动作,剔除多余步骤后制定标准化作业流程与计件激励,系统整理成《科学管理原理》一书出版。这套把生产管理量化、标准化的方法很快被汽车与制造业效仿,为随后的流水线生产铺平了管理基础。","links":["eco_fordism"],"src":"科学管理"},
{"id":"eco_drake_oil_well","t":"石油工业诞生 · 德雷克井","d":"eco","y":1859,"sub":"industry","lat":41.63,"lon":-79.67,"w":1,"gist":"一根铁管打进地下二十米,点灯的油从鲸身上换到了地底下。","detail":"退休列车长德雷克在宾夕法尼亚州蒂特斯维尔用打盐井的顿钻法钻出世界第一口商业采油井,以每桶几十美分的成本获取原油提炼煤油照明,价格远低于日渐稀缺的鲸油。钻井采油由此形成独立产业,蒂特斯维尔周边迅速涌入大批投机钻探者。","links":["eco_standard_oil_trust"],"src":"德雷克油井"},
{"id":"eco_pearl_street_station","t":"电气化 · 珍珠街电站","d":"eco","y":1882,"sub":"industry","lat":40.71,"lon":-74.01,"w":2,"gist":"一座电站同时给数百盏灯供电,照明第一次不用各家各户自备发电机。","detail":"爱迪生在曼哈顿珍珠街建成首座商用中央发电站,以直流电网络向周边数百家客户集中供应照明用电,取代了此前企业自建小型发电机的零散模式。集中发电、统一收费的商业模式此后被各大城市复制,电力逐渐成为像自来水一样的公共基础设施。","links":["eco_industrial_robot"],"src":"珍珠街发电站"},
{"id":"eco_synthetic_dye_industry","t":"化工巨头 · 合成染料与巴斯夫","d":"eco","y":1865,"sub":"industry","lat":49.48,"lon":8.44,"w":1,"gist":"从煤焦油里炼出紫色染料的意外发现,养出了一整个化工产业。","detail":"英国青年珀金从煤焦油废料中意外合成出苯胺紫染料,证明染料可以工业化人工制造而不必依赖天然植物。德国企业随即跟进研发合成染料,巴斯夫等公司在莱茵河畔建厂投产,逐渐从染料业务扩展成横跨化肥、药品的综合化工巨头。","links":[],"src":"巴斯夫"},
{"id":"eco_fairchild_planar","t":"半导体制造 · 仙童平面工艺","d":"eco","y":1957,"sub":"industry","lat":37.39,"lon":-122.08,"w":3,"gist":"给硅片盖一层氧化膜,晶体管第一次能像印刷一样批量复制。","detail":"八位工程师出走肖克利实验室,在山景城创立仙童半导体;两年后霍尔尼发明平面工艺,用氧化层保护并批量刻蚀晶体管结构,解决了晶体管良品率低、只能手工筛选的瓶颈。平面工艺让芯片得以规模化可靠量产,硅谷由此获得了自己的名字。","links":["ai"],"src":"仙童半导体"},
{"id":"eco_industrial_robot","t":"工业机器人 · 尤尼梅特","d":"eco","y":1961,"sub":"industry","lat":40.27,"lon":-74.7,"w":1,"gist":"一条液压机械臂顶班上岗,压铸车间第一次不再需要人手去搬烫模具。","detail":"发明家德沃尔设计出可编程液压机械臂尤尼梅特,由恩格尔伯格推动量产,安装进通用汽车新泽西工厂负责搬运高温压铸件。这是工业界第一台真正投入生产线使用的可编程机器人,此后机械臂逐步接管焊接、喷涂等重复性高危工序。","links":["globalization"],"src":"尤尼梅特"},
{"id":"eco_wheel_invention","t":"轮子的发明","d":"eco","y":-3500,"sub":"transport","lat":31.32,"lon":45.64,"w":3,"gist":"圆形代替了拖拽,货物第一次能被推着走而不是被拽着走。","detail":"两河流域先民把陶轮的圆形结构移植到运输工具上,造出带轮车轴的板车,大幅降低了陆地拖运重物的摩擦损耗。轮式车辆后续与畜力结合,催生出战车与货运马车,轮子与轴承的组合此后成为几乎所有陆地机械的基础结构。","links":["eco_railway"],"src":"轮子"},
{"id":"eco_qin_straight_road","t":"秦驰道网络","d":"eco","y":-212,"sub":"transport","lat":40.66,"lon":109.85,"w":1,"gist":"一条统一路宽的国道从咸阳直插草原,军情从此几天就能传到边境。","detail":"秦始皇命蒙恬修筑以咸阳为起点、直通北方九原郡的驰道网络,统一路面宽度并沿途设立驿站,骑兵与辎重车队可高速调度直抵长城沿线。这套早期国家级公路系统把边疆防御与中央政令的响应速度提升到此前无法想象的程度。","links":["eco_mongol_yam"],"src":"秦直道"},
{"id":"eco_safety_bicycle","t":"安全自行车","d":"eco","y":1885,"sub":"transport","lat":52.41,"lon":-1.51,"w":1,"gist":"两个一样大的轮子加链条,骑车第一次不用担心摔断脖子。","detail":"考文垂工程师斯塔利把此前前轮硕大易摔的高轮车改成前后等径、链条驱动后轮的结构,配合后续出现的充气轮胎,骑行变得安全省力且价格亲民。安全自行车迅速在欧美普及,也让不便驾驭高轮车的女性第一次获得了独立、廉价的个人代步工具。","links":["sci_wright"],"src":"安全自行车"},
{"id":"eco_panama_canal","t":"巴拿马运河","d":"eco","y":1914,"sub":"transport","lat":9.08,"lon":-79.68,"w":2,"gist":"凿穿一段地峡,太平洋到大西洋不用再绕道合恩角。","detail":"美国接手法国未完成的运河工程,用船闸系统抬升船只越过巴拿马地峡的山地地形,把太平洋与大西洋之间的航程缩短上万公里,船只不必再绕行南美洲最南端的合恩角。运河控制权长期由美国掌握,直至二十世纪末才移交巴拿马。","links":["globalization"],"src":"巴拿马运河"},
{"id":"eco_jet_age","t":"民航时代 · 喷气客机普及","d":"eco","y":1958,"sub":"transport","lat":40.64,"lon":-73.78,"w":1,"gist":"喷气发动机把跨大西洋航班的时间砍掉一半,越洋旅行第一次不再是有钱人的专利。","detail":"泛美航空引入波音707喷气客机开通纽约至巴黎航线,飞行时间比螺旋桨客机缩短近一半,单座运营成本随之下降。喷气客机迅速在各航空公司普及,越洋旅行从少数人的奢侈消费变成中产阶级也能负担的日常选项,推动了跨国商务与大众旅游业的兴起。","links":["globalization"],"src":"波音707"}
]}